README.md
setup.py
grr_api_client/__init__.py
grr_api_client/api.py
grr_api_client/api_shell.py
grr_api_client/api_shell_lib.py
grr_api_client/artifact.py
grr_api_client/client.py
grr_api_client/config.py
grr_api_client/context.py
grr_api_client/errors.py
grr_api_client/flow.py
grr_api_client/hunt.py
grr_api_client/metadata.py
grr_api_client/root.py
grr_api_client/types.py
grr_api_client/user.py
grr_api_client/utils.py
grr_api_client/utils_test.py
grr_api_client/vfs.py
grr_api_client/yara.py
grr_api_client.egg-info/PKG-INFO
grr_api_client.egg-info/SOURCES.txt
grr_api_client.egg-info/dependency_links.txt
grr_api_client.egg-info/entry_points.txt
grr_api_client.egg-info/requires.txt
grr_api_client.egg-info/top_level.txt
grr_api_client/connectors/__init__.py
grr_api_client/connectors/abstract.py
grr_api_client/connectors/http.py
grr_api_client/connectors/http_test.py