Metadata-Version: 2.4
Name: grr-api-client
Version: 4.0.0.post0
Summary: GRR API client library
Home-page: https://github.com/google/grr/tree/master/api_client/python
Maintainer: GRR Development Team
Maintainer-email: grr-dev@googlegroups.com
License: Apache License, Version 2.0
Requires-Dist: grr_response_proto==4.0.0post0
Requires-Dist: cryptography>=3.3.2
Requires-Dist: requests<3,>=2.25.1
Requires-Dist: Werkzeug<3,>=2.1.2
Dynamic: home-page
Dynamic: license
Dynamic: maintainer
Dynamic: maintainer-email
Dynamic: requires-dist
Dynamic: summary
